miose_toolkit_common/__init__.py
miose_toolkit_common/command.py
miose_toolkit_common/common.py
miose_toolkit_common/config.py
miose_toolkit_common/convert.py
miose_toolkit_common/dict.py
miose_toolkit_common/exceptions.py
miose_toolkit_common/fetch.py
miose_toolkit_common/file.py
miose_toolkit_common/funny.py
miose_toolkit_common/list.py
miose_toolkit_common/mxios.py
miose_toolkit_common/retry.py
miose_toolkit_common/url.py
miose_toolkit_common-0.3.7.dist-info/METADATA
miose_toolkit_common-0.3.7.dist-info/WHEEL
miose_toolkit_common-0.3.7.dist-info/RECORD
