Metadata-Version: 2.1
Name: miose-toolkit-common
Version: 0.3.7
Summary: Miose Toolkit 通用模块
Author: KroMiose
Author-email: li_xiangff@163.com
Requires-Python: >=3.8,<3.12
Classifier: Programming Language :: Python :: 3
Classifier: Programming Language :: Python :: 3.8
Classifier: Programming Language :: Python :: 3.9
Classifier: Programming Language :: Python :: 3.10
Classifier: Programming Language :: Python :: 3.11
Requires-Dist: aiohttp (>=3.9.4,<4.0.0)
Requires-Dist: cryptography (>=42.0.4)
Requires-Dist: poetry (>=1.6.1,<2.0.0)
Requires-Dist: pydantic (>=1.10,<3.0)
Requires-Dist: pyyaml (>=6.0.1,<7.0.0)
Requires-Dist: requests (>=2.31.0,<3.0.0)
